sphinxext/rediraffe.py
sphinxext_rediraffe-0.3.0.dist-info/licenses/LICENCE.rst
sphinxext_rediraffe-0.3.0.dist-info/WHEEL
sphinxext_rediraffe-0.3.0.dist-info/METADATA
sphinxext_rediraffe-0.3.0.dist-info/RECORD
