Metadata-Version: 2.4
Name: sphinxext-rediraffe
Version: 0.3.0
Summary: Sphinx Extension that redirects non-existent pages to working pages
Author-email: Vasista Vovveti <vasistavovveti@gmail.com>
Requires-Python: >=3.9
License-Expression: MIT
Classifier: Development Status :: 5 - Production/Stable
Classifier: Environment :: Plugins
Classifier: Environment :: Web Environment
Classifier: Framework :: Sphinx :: Extension
Classifier: Intended Audience :: Developers
Classifier: Natural Language :: English
Classifier: Operating System :: OS Independent
Classifier: Programming Language :: Python :: 3.9
Classifier: Programming Language :: Python :: 3.10
Classifier: Programming Language :: Python :: 3.11
Classifier: Programming Language :: Python :: 3.12
Classifier: Programming Language :: Python :: 3.13
Classifier: Programming Language :: Python
Classifier: Topic :: Documentation :: Sphinx
Classifier: Topic :: Documentation
Classifier: Topic :: Software Development :: Documentation
Classifier: Topic :: Text Processing
Classifier: Topic :: Utilities
License-File: LICENCE.rst
Requires-Dist: Sphinx>=6.0
Project-URL: Code, https://github.com/sphinx-doc/sphinxext-rediraffe/
Project-URL: Documentation, https://sphinxext-rediraffe.readthedocs.io/
Project-URL: Download, https://pypi.org/project/sphinxext-rediraffe/
Project-URL: Homepage, https://github.com/sphinx-doc/sphinxext-rediraffe/
Project-URL: Issue tracker, https://github.com/sphinx-doc/sphinxext-rediraffe/issues
